sqs_encrypted_extended_client/__init__.py
sqs_encrypted_extended_client/session.py
sqs_encrypted_extended_client-0.0.2.dist-info/LICENSE
sqs_encrypted_extended_client-0.0.2.dist-info/METADATA
sqs_encrypted_extended_client-0.0.2.dist-info/WHEEL
sqs_encrypted_extended_client-0.0.2.dist-info/top_level.txt
sqs_encrypted_extended_client-0.0.2.dist-info/RECORD
