Metadata-Version: 2.1
Name: sqs-encrypted-extended-client
Version: 0.0.2
Summary: Allows for per-queue KMS encryption of large messages in S3
Home-page: https://github.com/QuiNovas/sqs-extended-client
Author: Joseph Wortmann
Author-email: jwortmann@quinovas.com
License: Apache 2.0
Platform: UNKNOWN
Classifier: Development Status :: 4 - Beta
Classifier: Intended Audience :: Developers
Classifier: License :: OSI Approved :: Apache Software License
Classifier: Programming Language :: Python :: 3.7
Requires-Dist: sqs-extended-client
